gabb/__init__.py
gabb/auth.py
gabb/client.py
gabb/session.py
gabb-0.1.0.dist-info/LICENSE.txt
gabb-0.1.0.dist-info/METADATA
gabb-0.1.0.dist-info/WHEEL
gabb-0.1.0.dist-info/RECORD
