Metadata-Version: 2.1
Name: gabb
Version: 0.1.0
Summary: A Python wrapper around the services powering the Gabb smartwatch/smartphone.
License: Apache-2.0
Author: Ben Woods
Author-email: ben@benandkristin.info
Requires-Python: >=3.11,<4.0
Classifier: License :: OSI Approved :: Apache Software License
Classifier: Programming Language :: Python :: 3
Classifier: Programming Language :: Python :: 3.11
Requires-Dist: python-dateutil (>=2.8.2,<3.0.0)
Requires-Dist: requests (>=2.31.0,<3.0.0)
